nimfilt.py
nimfilt-1.0.dist-info/LICENSE
nimfilt-1.0.dist-info/METADATA
nimfilt-1.0.dist-info/WHEEL
nimfilt-1.0.dist-info/entry_points.txt
nimfilt-1.0.dist-info/top_level.txt
nimfilt-1.0.dist-info/RECORD
