Metadata-Version: 2.1
Name: nimfilt
Version: 1.0
Summary: A collection of modules and scripts to help with analyzing Nim binaries
Home-page: https://www.github.com/eset/nimfilt
Author: Alexandre Côté Cyr
Author-email: alexandre.cote@eset.com
License: BSD
Classifier: Development Status :: 5 - Production/Stable
Classifier: License :: OSI Approved :: BSD License
Classifier: Programming Language :: Python :: 3
Requires-Python: >=3
License-File: LICENSE
